mfdfloods/__init__.py
mfdfloods/__main__.py
mfdfloods/debug.py
mfdfloods/geotransform.py
mfdfloods/gtif.py
mfdfloods/hydrogram.py
mfdfloods/main.py
mfdfloods/matrix.py
mfdfloods-0.1.34.dist-info/LICENSE
mfdfloods-0.1.34.dist-info/METADATA
mfdfloods-0.1.34.dist-info/WHEEL
mfdfloods-0.1.34.dist-info/entry_points.txt
mfdfloods-0.1.34.dist-info/top_level.txt
mfdfloods-0.1.34.dist-info/RECORD
