Metadata-Version: 2.1
Name: mfdfloods
Version: 0.1.34
Summary: Multiple flow direction floods hydrodynamic modelation
Author-email: Orzo Cogorzo <orzocogorzo@hotmail.com>
Project-URL: Homepage, https://github.com/orzocogorzo/mfdfloods
Keywords: mfdfloods,mfd,flood,drainpaths,hidrology,downstreams,multiple flow direction
Classifier: Development Status :: 3 - Alpha
Classifier: Environment :: Console
Classifier: Intended Audience :: Science/Research
Classifier: Programming Language :: Python :: 3
Classifier: License :: OSI Approved :: MIT License
Classifier: Operating System :: OS Independent
Classifier: Topic :: Scientific/Engineering :: Hydrology
Requires-Python: >=3.8
License-File: LICENSE
Requires-Dist: numpy
Requires-Dist: richdem
Requires-Dist: gdal
